README.md
setup.py
yxspkg_data_icon.py
yxspkg_data_icon.egg-info/PKG-INFO
yxspkg_data_icon.egg-info/SOURCES.txt
yxspkg_data_icon.egg-info/dependency_links.txt
yxspkg_data_icon.egg-info/top_level.txt