Metadata-Version: 1.1
Name: yxspkg-data-icon
Version: 1.0
Summary: mydata
Home-page: https://github.com/blacksong
Author: blacksong
Author-email: blacksong@yeah.net
License: UNKNOWN
Platform: any
Classifier: Programming Language :: Python :: 3
Classifier: Operating System :: OS Independent
Classifier: Topic :: Software Development :: Libraries :: Python Modules
